Workbook

Sheet Planejamento Financeiro 
B1: Planejamento Financeiro
C2: Premissas de Crescimento
C3: Carg | D3: 0.08 | E3: 0.08 | F3: 0.08 | G3: 0.08 | H3: 0.08 | I3: 0.08 | J3: 0.08 | K3: 0.08 | L3: 0.08 | M3: 0.08 | N3: 0.08
C4: IPCA | D4: 0.021 | E4: 0.021 | F4: 0.021 | G4: 0.021 | H4: 0.021 | I4: 0.021 | J4: 0.021 | K4: 0.021 | L4: 0.021 | M4: 0.021 | N4: 0.021
C5: SGA | D5: 0.015 | E5: 0.015 | F5: 0.015 | G5: 0.015 | H5: 0.015 | I5: 0.015 | J5: 0.015 | K5: 0.015 | L5: 0.015 | M5: 0.015 | N5: 0.015
C6: Estrutura de custo | D6: 0.06 | E6: 0.06 | F6: 0.06 | G6: 0.06 | H6: 0.06 | I6: 0.06 | J6: 0.06 | K6: 0.06 | L6: 0.06 | M6: 0.06 | N6: 0.06
C7: Realizado | D7: Rolling Forecast | E7: Rolling Forecast | F7: Rolling Forecast | G7: Rolling Forecast | H7: Rolling Forecast | I7: Rolling Forecast | J7: Rolling Forecast | K7: Rolling Forecast | L7: Rolling Forecast | M7: Rolling Forecast | N7: Rolling Forecast
C8: Janeiro | D8: Fevereiro | E8: Março | F8: Abril | G8: Maio | H8: Junho | I8: Julho | J8: Agosto | K8: Setembro | L8: Outubro | M8: Novembro | N8: Dezembro | O8: Total
B9: Receita | C9: =SUM(C10:C12) -> 84000 | D9: =SUM(D10:D12) -> 90720 | E9: =SUM(E10:E12) -> 97977.6 | F9: =SUM(F10:F12) -> 105815.81 | G9: =SUM(G10:G12) -> 114281.07 | H9: =SUM(H10:H12) -> 123423.56 | I9: =SUM(I10:I12) -> 133297.44 | J9: =SUM(J10:J12) -> 143961.24 | ... N9: =SUM(N10:N12) -> 195857.68 | O9: =SUM(C9:N9) -> 1594078.6
B10: Vendas de produto | C10: 56000 | D10: =C10*(1+D3) -> 60480 | E10: =D10*(1+E3) -> 65318.4 | F10: =E10*(1+F3) -> 70543.872 | G10: =F10*(1+G3) -> 76187.382 | H10: =G10*(1+H3) -> 82282.372 | I10: =H10*(1+I3) -> 88864.962 | J10: =I10*(1+J3) -> 95974.159 | K10: =J10*(1+K3) -> 103652.09 | ... N10: =M10*(1+N3) -> 130571.78 | O10: =SUM(C10:N10) -> 1062719.1
B11: Verdas de serviços Prestados | C11: 25000 | D11: =C11*(1+D3) -> 27000 | E11: =D11*(1+E3) -> 29160 | F11: =E11*(1+F3) -> 31492.8 | G11: =F11*(1+G3) -> 34012.224 | H11: =G11*(1+H3) -> 36733.202 | I11: =H11*(1+I3) -> 39671.858 | J11: =I11*(1+J3) -> 42845.607 | K11: =J11*(1+K3) -> 46273.255 | ... N11: =M11*(1+N3) -> 58290.975 | O11: =SUM(C11:N11) -> 474428.16
B12: Outras Receitas | C12: 3000 | D12: =C12*(1+D3) -> 3240 | E12: =D12*(1+E3) -> 3499.2 | F12: =E12*(1+F3) -> 3779.136 | G12: =F12*(1+G3) -> 4081.4669 | H12: =G12*(1+H3) -> 4407.9842 | I12: =H12*(1+I3) -> 4760.623 | J12: =I12*(1+J3) -> 5141.4728 | K12: =J12*(1+K3) -> 5552.7906 | ... N12: =M12*(1+N3) -> 6994.917 | O12: =SUM(C12:N12) -> 56931.379
B14: Custo e Despesa | C14: =C15+C19+C25+C29 -> 57200 | D14: =D15+D19+D25+D29 -> 60718.078 | E14: =E15+E19+E25+E29 -> 65219.166 | F14: =F15+F19+F25+F29 -> 70071.203 | G14: =G15+G19+G25+G29 -> 75302.245 | H14: =H15+H19+H25+H29 -> 80942.62 | I14: =I15+I19+I25+I29 -> 87025.108 | J14: =J15+J19+J25+J29 -> 93585.144 | ... O14: =O15+O19+O25+O29 -> 1040963.1
B15: Custo Variaveis | C15: =SUM(C16:C17) -> 19000 | D15: =SUM(D16:D17) -> 20562.94 | E15: =SUM(E16:E17) -> 22254.447 | F15: =SUM(F16:F17) -> 24085.098 | G15: =SUM(G16:G17) -> 26066.338 | H15: =SUM(H16:H17) -> 28210.555 | I15: =SUM(I16:I17) -> 30531.156 | J15: =SUM(J16:J17) -> 33042.649 | ... N15: =SUM(N16:N17) -> 45331.624 | O15: =SUM(C15:N15) -> 365434.04
B16: Matéria --Prima | C16: 13000 | D16: =C16*(1+D4)*(1+D6) -> 14069.38 | E16: =D16*(1+E4)*(1+E6) -> 15226.727 | F16: =E16*(1+F4)*(1+F6) -> 16479.278 | G16: =F16*(1+G4)*(1+G6) -> 17834.863 | H16: =G16*(1+H4)*(1+H6) -> 19301.959 | I16: =H16*(1+I4)*(1+I6) -> 20889.738 | J16: =I16*(1+J4)*(1+J6) -> 22608.128 | K16: =J16*(1+K4)*(1+K6) -> 24467.873 | ... N16: =M16*(1+N4)*(1+N6) -> 31016.375 | O16: =SUM(C16:N16) -> 250033.81
B17: Custo de Fabricação | C17: 6000 | D17: =C17*(1+D4)*(1+D6) -> 6493.56 | E17: =D17*(1+E4)*(1+E6) -> 7027.7202 | F17: =E17*(1+F4)*(1+F6) -> 7605.8205 | G17: =F17*(1+G4)*(1+G6) -> 8231.4753 | H17: =G17*(1+H4)*(1+H6) -> 8908.5965 | I17: =H17*(1+I4)*(1+I6) -> 9641.4176 | J17: =I17*(1+J4)*(1+J6) -> 10434.521 | K17: =J17*(1+K4)*(1+K6) -> 11292.864 | ... N17: =M17*(1+N4)*(1+N6) -> 14315.25 | O17: =SUM(C17:N17) -> 115400.22
B19: Despesas Fixas | C19: =SUM(C20:C24) -> 15500 | D19: =SUM(D20:D24) -> 16062.882 | E19: =SUM(E20:E24) -> 17384.215 | F19: =SUM(F20:F24) -> 18814.241 | G19: =SUM(G20:G24) -> 20361.9 | H19: =SUM(H20:H24) -> 22036.87 | I19: =SUM(I20:I24) -> 23849.623 | J19: =SUM(J20:J24) -> 25811.493 | ... N19: =SUM(N20:N24) -> 35411.111 | O19: =SUM(C19:N19) -> 286119.34
B20: Aluguel | C20: 6000 | D20: =C20*(1+D4)*(1+D5) -> 6217.89 | E20: =D20*(1+E4)*(1+E6) -> 6729.3736 | F20: =E20*(1+F4)*(1+F6) -> 7282.9319 | G20: =F20*(1+G4)*(1+G6) -> 7882.0259 | H20: =G20*(1+H4)*(1+H6) -> 8530.4013 | I20: =H20*(1+I4)*(1+I6) -> 9232.1121 | J20: =I20*(1+J4)*(1+J6) -> 9991.5457 | K20: =J20*(1+K4)*(1+K6) -> 10813.45 | L20: =K20*(1+L4)*(1+L6) -> 11702.965 | ... N20: =M20*(1+N4)*(1+N6) -> 13707.527 | O20: =SUM(C20:N20) -> 110755.87
B21: Seguro | C21: 2000 | D21: =C21*(1+D4)*(1+D5) -> 2072.63 | E21: =D21*(1+E4)*(1+E6) -> 2243.1245 | F21: =E21*(1+F4)*(1+F6) -> 2427.644 | G21: =F21*(1+G4)*(1+G6) -> 2627.342 | H21: =G21*(1+H4)*(1+H6) -> 2843.4671 | I21: =H21*(1+I4)*(1+I6) -> 3077.3707 | J21: =I21*(1+J4)*(1+J6) -> 3330.5152 | K21: =J21*(1+K4)*(1+K6) -> 3604.4834 | L21: =K21*(1+L4)*(1+L6) -> 3900.9882 | ... N21: =M21*(1+N4)*(1+N6) -> 4569.1756 | O21: =SUM(C21:N21) -> 36918.624
B22: Sálario e Benefícios | C22: 3000 | D22: =C22*(1+D4)*(1+D5) -> 3108.945 | E22: =D22*(1+E4)*(1+E6) -> 3364.6868 | F22: =E22*(1+F4)*(1+F6) -> 3641.466 | G22: =F22*(1+G4)*(1+G6) -> 3941.0129 | H22: =G22*(1+H4)*(1+H6) -> 4265.2007 | I22: =H22*(1+I4)*(1+I6) -> 4616.0561 | J22: =I22*(1+J4)*(1+J6) -> 4995.7728 | K22: =J22*(1+K4)*(1+K6) -> 5406.7251 | L22: =K22*(1+L4)*(1+L6) -> 5851.4823 | ... N22: =M22*(1+N4)*(1+N6) -> 6853.7635 | O22: =SUM(C22:N22) -> 55377.936
B23: Serviços Publicos | C23: 1500 | D23: =C23*(1+D4)*(1+D5) -> 1554.4725 | E23: =D23*(1+E4)*(1+E6) -> 1682.3434 | F23: =E23*(1+F4)*(1+F6) -> 1820.733 | G23: =F23*(1+G4)*(1+G6) -> 1970.5065 | H23: =G23*(1+H4)*(1+H6) -> 2132.6003 | I23: =H23*(1+I4)*(1+I6) -> 2308.028 | J23: =I23*(1+J4)*(1+J6) -> 2497.8864 | K23: =J23*(1+K4)*(1+K6) -> 2703.3626 | L23: =K23*(1+L4)*(1+L6) -> 2925.7412 | ... N23: =M23*(1+N4)*(1+N6) -> 3426.8817 | O23: =SUM(C23:N23) -> 27688.968
B24: Depreciação& Amortização | C24: 3000 | D24: =C24*(1+D4)*(1+D5) -> 3108.945 | E24: =D24*(1+E4)*(1+E6) -> 3364.6868 | F24: =E24*(1+F4)*(1+F6) -> 3641.466 | G24: =F24*(1+G4)*(1+G6) -> 3941.0129 | H24: =G24*(1+H4)*(1+H6) -> 4265.2007 | I24: =H24*(1+I4)*(1+I6) -> 4616.0561 | J24: =I24*(1+J4)*(1+J6) -> 4995.7728 | K24: =J24*(1+K4)*(1+K6) -> 5406.7251 | L24: =K24*(1+L4)*(1+L6) -> 5851.4823 | ... N24: =M24*(1+N4)*(1+N6) -> 6853.7635 | O24: =SUM(C24:N24) -> 55377.936
B25: Despesas Variaveis | C25: =SUM(C26:C28) -> 9700 | D25: =SUM(D26:D28) -> 10052.255 | E25: =SUM(E26:E28) -> 10417.303 | F25: =SUM(F26:F28) -> 10795.608 | G25: =SUM(G26:G28) -> 11187.65 | H25: =SUM(H26:H28) -> 11593.93 | I25: =SUM(I26:I28) -> 12014.963 | J25: =SUM(J26:J28) -> 12451.286 | ... N25: =SUM(N26:N28) -> 14360.89 | O25: =SUM(C25:N25) -> 142707.03
B26: Comissões | C26: 3000 | D26: =C26*(1+D4)*(1+D5) -> 3108.945 | E26: =D26*(1+E4)*(1+E5) -> 3221.8463 | F26: =E26*(1+F4)*(1+F5) -> 3338.8477 | G26: =F26*(1+G4)*(1+G5) -> 3460.0979 | H26: =G26*(1+H4)*(1+H5) -> 3585.7514 | I26: =H26*(1+I4)*(1+I5) -> 3715.968 | J26: =I26*(1+J4)*(1+J5) -> 3850.9133 | K26: =J26*(1+K4)*(1+K5) -> 3990.7593 | ... N26: =M26*(1+N4)*(1+N5) -> 4441.5124 | O26: =SUM(C26:N26) -> 44136.196
B27: Markentig | C27: 2500 | D27: =C27*(1+D4)*(1+D5) -> 2590.7875 | E27: =D27*(1+E4)*(1+E5) -> 2684.8719 | F27: =E27*(1+F4)*(1+F5) -> 2782.3731 | G27: =F27*(1+G4)*(1+G5) -> 2883.415 | H27: =G27*(1+H4)*(1+H5) -> 2988.1262 | I27: =H27*(1+I4)*(1+I5) -> 3096.64 | J27: =I27*(1+J4)*(1+J5) -> 3209.0944 | K27: =J27*(1+K4)*(1+K5) -> 3325.6327 | ... N27: =M27*(1+N4)*(1+N5) -> 3701.2604 | O27: =SUM(C27:N27) -> 36780.163
B28: Fretes e Logistica | C28: 4200 | D28: =C28*(1+D4)*(1+D5) -> 4352.523 | E28: =D28*(1+E4)*(1+E5) -> 4510.5849 | F28: =E28*(1+F4)*(1+F5) -> 4674.3868 | G28: =F28*(1+G4)*(1+G5) -> 4844.1371 | H28: =G28*(1+H4)*(1+H5) -> 5020.052 | I28: =H28*(1+I4)*(1+I5) -> 5202.3551 | J28: =I28*(1+J4)*(1+J5) -> 5391.2787 | K28: =J28*(1+K4)*(1+K5) -> 5587.063 | ... N28: =M28*(1+N4)*(1+N5) -> 6218.1174 | O28: =SUM(C28:N28) -> 61790.674
B29: Outras Despesas | C29: =SUM(C30:C30) -> 13000 | D29: =SUM(D30:D30) -> 14040 | E29: =SUM(E30:E30) -> 15163.2 | F29: =SUM(F30:F30) -> 16376.256 | G29: =SUM(G30:G30) -> 17686.356 | H29: =SUM(H30:H30) -> 19101.265 | I29: =SUM(I30:I30) -> 20629.366 | J29: =SUM(J30:J30) -> 22279.715 | ... N29: =SUM(N30:N30) -> 30311.307 | O29: =SUM(C29:N29) -> 246702.64
B30: Impostos | C30: 13000 | D30: =C30*(1+8%) -> 14040 | E30: =D30*(1+8%) -> 15163.2 | F30: =E30*(1+8%) -> 16376.256 | G30: =F30*(1+8%) -> 17686.356 | H30: =G30*(1+8%) -> 19101.265 | I30: =H30*(1+8%) -> 20629.366 | J30: =I30*(1+8%) -> 22279.715 | K30: =J30*(1+8%) -> 24062.093 | ... O30: =N30*(1+8%) -> 32736.212
B32: Fluxo de caixa operacional | C32: =C9-C14 -> 26800 | D32: =D9-D14 -> 30001.922 | E32: =E9-E14 -> 32758.434 | F32: =F9-F14 -> 35744.605 | G32: =G9-G14 -> 38978.827 | H32: =H9-H14 -> 42480.938 | I32: =I9-I14 -> 46272.335 | J32: =J9-J14 -> 50376.095 | ... N32: =N9-N14 -> 70442.743 | O32: =SUM(C32:N32) -> 553115.57
B33: Investimento | C33: 6000 | E33: 4000 | G33: 2000 | H33: 1500 | I33: 3600 | K33: 6000 | M33: 10000 | N33: 10000 | O33: =SUM(C33:N33) -> 43100
B34: Investimento Acumulado | C34: =C33 -> 6000 | D34: =D33+C34 -> 6000 | E34: =E33+D34 -> 10000 | F34: =F33+E34 -> 10000 | G34: =G33+F34 -> 12000 | H34: =H33+G34 -> 13500 | I34: =I33+H34 -> 17100 | J34: =J33+I34 -> 17100 | K34: =K33+J34 -> 23100 | ... N34: =N33+M34 -> 43100 | O34: =SUM(C34:N34) -> 214100
B36: Fluxo de caixa Livre da Empresa (FCE) | C36: =C32-C33 -> 20800 | D36: =D32-D33 -> 30001.922 | E36: =E32-E33 -> 28758.434 | F36: =F32-F33 -> 35744.605 | G36: =G32-G33 -> 36978.827 | H36: =H32-H33 -> 40980.938 | I36: =I32-I33 -> 42672.335 | J36: =J32-J33 -> 50376.095 | ... N36: =N32-N33 -> 60442.743 | O36: =SUM(C36:N36) -> 510015.57
B38: Emprestimo e Financiamento | C38: 15000 | D38: 15000 | E38: 15000 | F38: 15000 | G38: 15000 | H38: 15000 | I38: 15000 | J38: 15000 | K38: 15000 | L38: 15000 | M38: 15000 | N38: 15000 | O38: =SUM(C38:N38) -> 180000
B40: Lucro Liquido do Período | C40: =C36+C38 -> 35800 | D40: =D36+D38 -> 45001.922 | E40: =E36+E38 -> 43758.434 | F40: =F36+F38 -> 50744.605 | G40: =G36+G38 -> 51978.827 | H40: =H36+H38 -> 55980.938 | I40: =I36+I38 -> 57672.335 | J40: =J36+J38 -> 65376.095 | ... N40: =N36+N38 -> 75442.743 | O40: =SUM(C40:N40) -> 690015.57
B41: Lucro Liquido Acumulado | C41: =C40 -> 35800 | D41: =C41+D40 -> 80801.922 | E41: =D41+E40 -> 124560.36 | F41: =E41+F40 -> 175304.96 | G41: =F41+G40 -> 227283.79 | H41: =G41+H40 -> 283264.73 | I41: =H41+I40 -> 340937.06 | J41: =I41+J40 -> 406313.16 | K41: =J41+K40 -> 470130.26 | ... N41: =M41+N40 -> 690015.57 | O41: =SUM(C41:N41) -> 3993737.1

Sheet Indicadores Financeiros  
A2: Indicadores de Rentabilidade | B2: Jan | C2: Fev | D2: Mar | E2: Abr | F2: Mai | G2: Jun | H2: Jul | I2: Ago | J2: Set | K2: Out | L2: Nov | M2: Dez | N2: Ano
A3: Margem Bruta | B3: =('Planejamento Financeiro '!C9-'Planejamento Financeiro '!C15)/'Planejamento Financeiro '!C9 -> 0.77380952 | C3: =('Planejamento Financeiro '!D9-'Planejamento Financeiro '!D15)/'Planejamento Financeiro '!D9 -> 0.7733362 | D3: =('Planejamento Financeiro '!E9-'Planejamento Financeiro '!E15)/'Planejamento Financeiro '!E9 -> 0.77286188 | E3: =('Planejamento Financeiro '!F9-'Planejamento Financeiro '!F15)/'Planejamento Financeiro '!F9 -> 0.77238658 | F3: =('Planejamento Financeiro '!G9-'Planejamento Financeiro '!G15)/'Planejamento Financeiro '!G9 -> 0.77191027 | G3: =('Planejamento Financeiro '!H9-'Planejamento Financeiro '!H15)/'Planejamento Financeiro '!H9 -> 0.77143298 | H3: =('Planejamento Financeiro '!I9-'Planejamento Financeiro '!I15)/'Planejamento Financeiro '!I9 -> 0.77095468 | I3: =('Planejamento Financeiro '!J9-'Planejamento Financeiro '!J15)/'Planejamento Financeiro '!J9 -> 0.77047538 | ... N3: =('Planejamento Financeiro '!O9-'Planejamento Financeiro '!O15)/'Planejamento Financeiro '!O9 -> 0.77075532
A4: Margem Operacional | B4: ='Planejamento Financeiro '!C32/'Planejamento Financeiro '!C9 -> 0.31904762 | C4: ='Planejamento Financeiro '!D32/'Planejamento Financeiro '!D9 -> 0.33070902 | D4: ='Planejamento Financeiro '!E32/'Planejamento Financeiro '!E9 -> 0.33434616 | E4: ='Planejamento Financeiro '!F32/'Planejamento Financeiro '!F9 -> 0.33780024 | F4: ='Planejamento Financeiro '!G32/'Planejamento Financeiro '!G9 -> 0.34107859 | G4: ='Planejamento Financeiro '!H32/'Planejamento Financeiro '!H9 -> 0.34418825 | H4: ='Planejamento Financeiro '!I32/'Planejamento Financeiro '!I9 -> 0.34713595 | I4: ='Planejamento Financeiro '!J32/'Planejamento Financeiro '!J9 -> 0.34992819 | ... N4: ='Planejamento Financeiro '!O32/'Planejamento Financeiro '!O9 -> 0.34698136
A5: Margem Liquida | B5: ='Planejamento Financeiro '!C40/'Planejamento Financeiro '!C9 -> 0.42619048 | C5: ='Planejamento Financeiro '!D40/'Planejamento Financeiro '!D9 -> 0.49605293 | D5: ='Planejamento Financeiro '!E40/'Planejamento Financeiro '!E9 -> 0.44661672 | E5: ='Planejamento Financeiro '!F40/'Planejamento Financeiro '!F9 -> 0.479556 | F5: ='Planejamento Financeiro '!G40/'Planejamento Financeiro '!G9 -> 0.45483321 | G5: ='Planejamento Financeiro '!H40/'Planejamento Financeiro '!H9 -> 0.45356769 | H5: ='Planejamento Financeiro '!I40/'Planejamento Financeiro '!I9 -> 0.43265897 | I5: ='Planejamento Financeiro '!J40/'Planejamento Financeiro '!J9 -> 0.4541229 | ... N5: ='Planejamento Financeiro '!O40/'Planejamento Financeiro '!O9 -> 0.43286169
A7: Indicadores de Liquidez e Caixa | B7: Jan | C7: Fev | D7: Mar | E7: Abr | F7: Mai | G7: Jun | H7: Jul | I7: Ago | J7: Set | K7: Out | L7: Nov | M7: Dez | N7: Ano
A8: Taxa de Conversão de Caixa | B8: ='Planejamento Financeiro '!C36/'Planejamento Financeiro '!C40 -> 0.58100559 | C8: ='Planejamento Financeiro '!D36/'Planejamento Financeiro '!D40 -> 0.6666809 | D8: ='Planejamento Financeiro '!E36/'Planejamento Financeiro '!E40 -> 0.65720894 | E8: ='Planejamento Financeiro '!F36/'Planejamento Financeiro '!F40 -> 0.70440208 | F8: ='Planejamento Financeiro '!G36/'Planejamento Financeiro '!G40 -> 0.71142096 | G8: ='Planejamento Financeiro '!H36/'Planejamento Financeiro '!H40 -> 0.73205165 | H8: ='Planejamento Financeiro '!I36/'Planejamento Financeiro '!I40 -> 0.73990996 | I8: ='Planejamento Financeiro '!J36/'Planejamento Financeiro '!J40 -> 0.77055834 | ... N8: ='Planejamento Financeiro '!O36/'Planejamento Financeiro '!O40 -> 0.73913632
A9: Cobertura de Investimento | B9: ='Planejamento Financeiro '!C32/'Planejamento Financeiro '!C38 -> 1.7866667 | C9: ='Planejamento Financeiro '!D32/'Planejamento Financeiro '!D38 -> 2.0001281 | D9: ='Planejamento Financeiro '!E32/'Planejamento Financeiro '!E38 -> 2.1838956 | E9: ='Planejamento Financeiro '!F32/'Planejamento Financeiro '!F38 -> 2.3829737 | F9: ='Planejamento Financeiro '!G32/'Planejamento Financeiro '!G38 -> 2.5985885 | G9: ='Planejamento Financeiro '!H32/'Planejamento Financeiro '!H38 -> 2.8320626 | H9: ='Planejamento Financeiro '!I32/'Planejamento Financeiro '!I38 -> 3.0848223 | I9: ='Planejamento Financeiro '!J32/'Planejamento Financeiro '!J38 -> 3.3584063 | ... N9: ='Planejamento Financeiro '!O32/'Planejamento Financeiro '!O38 -> 3.0728643
A12: Indicadores de Crescimento | B12: Jan | C12: Fev | D12: Mar | E12: Abr | F12: Mai | G12: Jun | H12: Jul | I12: Ago | J12: Set | K12: Out | L12: Nov | M12: Dez | N12: Ano
A13: Taxa de Crescimento da Receita | C13: =('Planejamento Financeiro '!D9-'Planejamento Financeiro '!C9)/'Planejamento Financeiro '!C9 -> 0.08 | D13: =('Planejamento Financeiro '!E9-'Planejamento Financeiro '!D9)/'Planejamento Financeiro '!D9 -> 0.08 | E13: =('Planejamento Financeiro '!F9-'Planejamento Financeiro '!E9)/'Planejamento Financeiro '!E9 -> 0.08 | F13: =('Planejamento Financeiro '!G9-'Planejamento Financeiro '!F9)/'Planejamento Financeiro '!F9 -> 0.08 | G13: =('Planejamento Financeiro '!H9-'Planejamento Financeiro '!G9)/'Planejamento Financeiro '!G9 -> 0.08 | H13: =('Planejamento Financeiro '!I9-'Planejamento Financeiro '!H9)/'Planejamento Financeiro '!H9 -> 0.08 | I13: =('Planejamento Financeiro '!J9-'Planejamento Financeiro '!I9)/'Planejamento Financeiro '!I9 -> 0.08 | J13: =('Planejamento Financeiro '!K9-'Planejamento Financeiro '!J9)/'Planejamento Financeiro '!J9 -> 0.08 | ... M13: =('Planejamento Financeiro '!N9-'Planejamento Financeiro '!M9)/'Planejamento Financeiro '!M9 -> 0.08
A14: Taxa de Crescimento do Lucro Líquido | C14: =('Planejamento Financeiro '!D40-'Planejamento Financeiro '!C40)/'Planejamento Financeiro '!C40 -> 0.25703693 | D14: =('Planejamento Financeiro '!E40-'Planejamento Financeiro '!D40)/'Planejamento Financeiro '!D40 -> -0.027631882 | E14: =('Planejamento Financeiro '!F40-'Planejamento Financeiro '!E40)/'Planejamento Financeiro '!E40 -> 0.15965314 | F14: =('Planejamento Financeiro '!G40-'Planejamento Financeiro '!F40)/'Planejamento Financeiro '!F40 -> 0.024322232 | G14: =('Planejamento Financeiro '!H40-'Planejamento Financeiro '!G40)/'Planejamento Financeiro '!G40 -> 0.07699502 | H14: =('Planejamento Financeiro '!I40-'Planejamento Financeiro '!H40)/'Planejamento Financeiro '!H40 -> 0.030213797 | I14: =('Planejamento Financeiro '!J40-'Planejamento Financeiro '!I40)/'Planejamento Financeiro '!I40 -> 0.13357808 | J14: =('Planejamento Financeiro '!K40-'Planejamento Financeiro '!J40)/'Planejamento Financeiro '!J40 -> -0.023846458 | ... M14: =('Planejamento Financeiro '!N40-'Planejamento Financeiro '!M40)/'Planejamento Financeiro '!M40 -> 0.080526531
A15: Retorno sobre Investimento (ROI) | B15: ='Planejamento Financeiro '!C40/'Planejamento Financeiro '!C34 -> 5.9666667 | C15: ='Planejamento Financeiro '!D40/'Planejamento Financeiro '!D34 -> 7.5003203 | D15: ='Planejamento Financeiro '!E40/'Planejamento Financeiro '!E34 -> 4.3758434 | E15: ='Planejamento Financeiro '!F40/'Planejamento Financeiro '!F34 -> 5.0744605 | F15: ='Planejamento Financeiro '!G40/'Planejamento Financeiro '!G34 -> 4.331569 | G15: ='Planejamento Financeiro '!H40/'Planejamento Financeiro '!H34 -> 4.1467362 | H15: ='Planejamento Financeiro '!I40/'Planejamento Financeiro '!I34 -> 3.3726512 | I15: ='Planejamento Financeiro '!J40/'Planejamento Financeiro '!J34 -> 3.8231634 | ... N15: ='Planejamento Financeiro '!O40/'Planejamento Financeiro '!O34 -> 3.2228658
A17: Indicadores de Estrutura de Capital | B17: Jan | C17: Fev | D17: Mar | E17: Abr | F17: Mai | G17: Jun | H17: Jul | I17: Ago | J17: Set | K17: Out | L17: Nov | M17: Dez | N17: Ano
A18: Alavancagem Financeira | B18: ='Planejamento Financeiro '!C40/'Planejamento Financeiro '!C32 -> 1.3358209 | C18: ='Planejamento Financeiro '!D40/'Planejamento Financeiro '!D32 -> 1.499968 | D18: ='Planejamento Financeiro '!E40/'Planejamento Financeiro '!E32 -> 1.3357914 | E18: ='Planejamento Financeiro '!F40/'Planejamento Financeiro '!F32 -> 1.4196437 | F18: ='Planejamento Financeiro '!G40/'Planejamento Financeiro '!G32 -> 1.3335144 | G18: ='Planejamento Financeiro '!H40/'Planejamento Financeiro '!H32 -> 1.3177896 | H18: ='Planejamento Financeiro '!I40/'Planejamento Financeiro '!I32 -> 1.2463675 | I18: ='Planejamento Financeiro '!J40/'Planejamento Financeiro '!J32 -> 1.2977603 | ... N18: ='Planejamento Financeiro '!O40/'Planejamento Financeiro '!O32 -> 1.247507
A20: Indicadores de Eficiência | B20: Jan | C20: Fev | D20: Mar | E20: Abr | F20: Mai | G20: Jun | H20: Jul | I20: Ago | J20: Set | K20: Out | L20: Nov | M20: Dez | N20: Ano
A21: Custo sobre Receita | B21: ='Planejamento Financeiro '!C14/'Planejamento Financeiro '!C9 -> 0.68095238 | C21: ='Planejamento Financeiro '!D14/'Planejamento Financeiro '!D9 -> 0.66929098 | D21: ='Planejamento Financeiro '!E14/'Planejamento Financeiro '!E9 -> 0.66565384 | E21: ='Planejamento Financeiro '!F14/'Planejamento Financeiro '!F9 -> 0.66219976 | F21: ='Planejamento Financeiro '!G14/'Planejamento Financeiro '!G9 -> 0.65892141 | G21: ='Planejamento Financeiro '!H14/'Planejamento Financeiro '!H9 -> 0.65581175 | H21: ='Planejamento Financeiro '!I14/'Planejamento Financeiro '!I9 -> 0.65286405 | I21: ='Planejamento Financeiro '!J14/'Planejamento Financeiro '!J9 -> 0.65007181 | ... N21: ='Planejamento Financeiro '!O14/'Planejamento Financeiro '!O9 -> 0.65301864

Sheet Dashaboard
